License.txt
MANIFEST.in
README.rst
requirements.txt
setup.py
pyrcmd/VERSION
pyrcmd/__init__.py
pyrcmd/ssh.py
pyrcmd.egg-info/PKG-INFO
pyrcmd.egg-info/SOURCES.txt
pyrcmd.egg-info/dependency_links.txt
pyrcmd.egg-info/requires.txt
pyrcmd.egg-info/top_level.txt
pyrcmd/tests/__init__.py
pyrcmd/tests/test_ssh.py